MANIFEST.in
README.rst
setup.cfg
setup.py
accounts_shared/__init__.py
accounts_shared/admin.py
accounts_shared/apps.py
accounts_shared/choices.py
accounts_shared/countries.py
accounts_shared/enums.py
accounts_shared/managers.py
accounts_shared/models.py
accounts_shared/serializers.py
accounts_shared/tests.py
accounts_shared/urls.py
accounts_shared/views.py
accounts_shared.egg-info/PKG-INFO
accounts_shared.egg-info/SOURCES.txt
accounts_shared.egg-info/dependency_links.txt
accounts_shared.egg-info/requires.txt
accounts_shared.egg-info/top_level.txt
accounts_shared/filters/__init__.py
accounts_shared/filters/filters.py
accounts_shared/migrations/0001_initial.py
accounts_shared/migrations/0002_businessclient_creditlimit_and_more.py
accounts_shared/migrations/0003_company_plan.py
accounts_shared/migrations/__init__.py
accounts_shared/reports/__init__.py
accounts_shared/reports/accounts_reports.py
accounts_shared/reports/business_clients_reports.py